LICENSE
README.md
pyproject.toml
setup.cfg
setup.py
src/Nemesis/Nemesis.py
src/Nemesis/__init__.py
src/Nemesis/lib/Color.py
src/Nemesis/lib/Engine.py
src/Nemesis/lib/Functions.py
src/Nemesis/lib/Globals.py
src/Nemesis/lib/PathFunctions.py
src/Nemesis/lib/Scan.py
src/Nemesis/lib/__init__.py
src/nemesis_scan.egg-info/PKG-INFO
src/nemesis_scan.egg-info/SOURCES.txt
src/nemesis_scan.egg-info/dependency_links.txt
src/nemesis_scan.egg-info/entry_points.txt
src/nemesis_scan.egg-info/requires.txt
src/nemesis_scan.egg-info/top_level.txt