Metadata-Version: 2.1
Name: nemesis-scan
Version: 1.0.3
Summary: A tool for scanning urls
Home-page: https://github.com/machinexa2/Nemesis
Author: Machine Yadav
Author-email: machinexa@gmail.com
License: MIT
Download-URL: https://github.com/machinexa2/Nemesis/archive/refs/tags/v1.2.tar.gz
Keywords: tool,url,scan,hacking
Platform: UNKNOWN
Classifier: Programming Language :: Python :: 3
Classifier: License :: OSI Approved :: MIT License
Classifier: Operating System :: OS Independent
Requires-Python: >=3.8
